atsphinx/bulma/__init__.py
atsphinx/bulma/py.typed
atsphinx/bulma/translator.py
atsphinx/bulma/components/__init__.py
atsphinx/bulma/components/menu.py
atsphinx/bulma/components/messages.py
atsphinx/bulma/components/navbar.py
atsphinx/bulma/layout/__init__.py
atsphinx/bulma/layout/hero.py
atsphinx/bulma/themes/__init__.py
atsphinx/bulma/themes/bulma_basic/__init__.py
atsphinx/bulma/themes/bulma_basic/layout.html
atsphinx/bulma/themes/bulma_basic/page.html
atsphinx/bulma/themes/bulma_basic/search.html
atsphinx/bulma/themes/bulma_basic/theme.toml
atsphinx/bulma/themes/bulma_basic/sidebar/globaltoc.html
atsphinx/bulma/themes/bulma_basic/sidebar/line.html
atsphinx/bulma/themes/bulma_basic/sidebar/localtoc.html
atsphinx/bulma/themes/bulma_basic/sidebar/logo.html
atsphinx/bulma/themes/bulma_basic/sidebar/relations.html
atsphinx/bulma/themes/bulma_basic/sidebar/searchbox.html
atsphinx/bulma/themes/bulma_basic/sidebar/sourcelink.html
atsphinx/bulma/themes/bulma_basic/static/style.css_t
atsphinx/bulma/themes/bulma_basic/static/theme.js
atsphinx_bulma-0.4.1.dist-info/METADATA
atsphinx_bulma-0.4.1.dist-info/WHEEL
atsphinx_bulma-0.4.1.dist-info/entry_points.txt
atsphinx_bulma-0.4.1.dist-info/licenses/LICENSE
atsphinx_bulma-0.4.1.dist-info/RECORD
