Metadata-Version: 2.4
Name: atsphinx-bulma
Version: 0.4.1
Summary: Bluma using suite for Sphinx.
Project-URL: Home, https://github.com/atsphinx/bulma
Project-URL: Documentation, https://atsphinx.github.io/bulma
Author-email: Kazuya Takei <myself@attakei.net>
License-Expression: Apache-2.0
License-File: LICENSE
Classifier: Development Status :: 4 - Beta
Classifier: Framework :: Sphinx
Classifier: Framework :: Sphinx :: Extension
Classifier: Intended Audience :: Developers
Classifier: License :: OSI Approved :: Apache Software License
Classifier: Operating System :: OS Independent
Classifier: Programming Language :: Python
Classifier: Programming Language :: Python :: 3 :: Only
Classifier: Programming Language :: Python :: 3.10
Classifier: Programming Language :: Python :: 3.11
Classifier: Programming Language :: Python :: 3.12
Classifier: Programming Language :: Python :: 3.13
Classifier: Programming Language :: Python :: 3.14
Classifier: Topic :: Documentation
Classifier: Topic :: Documentation :: Sphinx
Classifier: Topic :: Software Development
Classifier: Topic :: Software Development :: Documentation
Classifier: Topic :: Software Development :: Libraries
Classifier: Topic :: Software Development :: Libraries :: Python Modules
Classifier: Topic :: Text Processing
Classifier: Topic :: Text Processing :: Markup
Classifier: Topic :: Text Processing :: Markup :: reStructuredText
Requires-Python: >=3.10
Requires-Dist: beautifulsoup4>=4
Requires-Dist: sphinx>=7.3.0
Requires-Dist: typing-extensions>=4.12.2
